Workbook

Sheet 7.数据看板
A1: 项目执行预算管理与分析预警数据看板
A3: 关键指标概览
A5: 项目总数 | C5: 合同总金额 | E5: 已收款金额
A6: =COUNTA('1.项目合同总览表'!B5:B20) | C6: =SUM('1.项目合同总览表'!D5:D20) | E6: =SUM('1.项目合同总览表'!E5:E20)
A7: 未收款金额 | C7: 整体收款进度 | E7: 整体开票进度
A8: =SUM('1.项目合同总览表'!G5:G20) | C8: ='1.项目合同总览表'!E12/'1.项目合同总览表'!D12 | E8: ='1.项目合同总览表'!H12/'1.项目合同总览表'!D12
A10: 风险分布统计
A12: 高风险项目 | B12: =COUNTIF('6.预警分析表'!H4:H20,"高风险") | C12: 中风险项目 | D12: =COUNTIF('6.预警分析表'!H4:H20,"中风险") | E12: 低风险项目 | F12: =COUNTIF('6.预警分析表'!H4:H20,"低风险")
A15: 项目状态分布
A17: 已完成 | B17: =COUNTIF('1.项目合同总览表'!J5:J20,"已完成")
A18: 执行中 | B18: =COUNTIF('1.项目合同总览表'!J5:J20,"执行中")
A19: 初期阶段 | B19: =COUNTIF('1.项目合同总览表'!J5:J20,"初期阶段")
A20: 未启动 | B20: =COUNTIF('1.项目合同总览表'!J5:J20,"未启动")

Sheet 1.项目合同总览表
A1: 项目执行预算管理与分析预警管理台帐
A2: 项目合同总览表
A4: 序号 | B4: 项目名称 | C4: 客户单位 | D4: 合同金额 | E4: 已收款金额 | F4: 收款进度 | G4: 未收款金额 | H4: 已开票金额 | I4: 开票进度 | J4: 项目状态 | K4: 项目联系人
A5: 1 | B5: 静象文旅 | C5: 静象文旅 | D5: 110000 | E5: 66000 | F5: 60.0% | G5: 44000 | H5: 66000 | I5: 60.0% | J5: 执行中 | K5: 赵宇涵
A6: 2 | B6: 滨海农商 | C6: 津北数字集团 | D6: 80000 | E6: 40000 | F6: 50.0% | G6: 40000 | H6: 40000 | I6: 50.0% | J6: 执行中 | K6: 高洁
A7: 3 | B7: 随行科技 | C7: 津北数字集团 | D7: 94400 | E7: 94400 | F7: 100.0% | G7: 0 | H7: 94400 | I7: 100.0% | J7: 已完成 | K7: 赵宇涵
A8: 4 | B8: 骏铭科技 | C8: 天津数据资产登记评估中心 | D8: 171000 | E8: 90000 | F8: 52.6% | G8: 81000 | H8: 90000 | I8: 52.6% | J8: 执行中 | K8: 高洁
A9: 5 | B9: 光电高斯 | C9: 天津数据资产登记评估中心 | D9: 225000 | E9: 108000 | F9: 48.0% | G9: 117000 | H9: 108000 | I9: 48.0% | J9: 初期阶段 | K9: 高洁
A10: 6 | B10: 中交疏浚 | C10: 天津数据资产登记评估中心 | D10: 180000 | E10: 0 | F10: 0.0% | G10: 180000 | H10: 72000 | I10: 40.0% | J10: 未启动 | K10: 赵宇涵
C11: 合计 | D11: =SUM(D5:D10) | E11: =SUM(E5:E10) | F11: =E11/D11 | G11: =SUM(G5:G10) | H11: =SUM(H5:H10) | I11: =H11/D11

Sheet 2.收款执行跟踪表
A1: 收款执行跟踪表
A3: 序号 | B3: 项目名称 | C3: 合同金额 | D3: 已收款金额 | E3: 收款进度 | F3: 未收款金额 | G3: 预计收款时间 | H3: 收款风险等级 | I3: 收款预警 | J3: 备注
A4: 1 | B4: 静象文旅 | C4: 110000 | D4: 66000 | E4: 0.6 | F4: 44000 | G4: 待确认 | H4: 低风险 | I4: 正常
A5: 2 | B5: 滨海农商 | C5: 80000 | D5: 40000 | E5: 0.5 | F5: 40000 | G5: 待确认 | H5: 低风险 | I5: 正常
A6: 3 | B6: 随行科技 | C6: 94400 | D6: 94400 | E6: 1 | F6: 0 | G6: 待确认 | H6: 无风险 | I6: - | J6: 项目已完成
A7: 4 | B7: 骏铭科技 | C7: 171000 | D7: 90000 | E7: 0.52631579 | F7: 81000 | G7: 待确认 | H7: 低风险 | I7: 正常
A8: 5 | B8: 光电高斯 | C8: 225000 | D8: 108000 | E8: 0.48 | F8: 117000 | G8: 待确认 | H8: 中风险 | I8: ⚠ 收款进度偏低
A9: 6 | B9: 中交疏浚 | C9: 180000 | D9: 0 | E9: 0 | F9: 180000 | G9: 待确认 | H9: 高风险 | I9: ⚠ 项目未启动收款
B10: 合计 | C10: =SUM(C4:C9) | D10: =SUM(D4:D9) | E10: =D10/C10 | F10: =SUM(F4:F9)

Sheet 3.开票管理表
A1: 开票管理表
A3: 序号 | B3: 项目名称 | C3: 合同金额 | D3: 已开票金额 | E3: 开票进度 | F3: 剩余发票金额 | G3: 待开票金额 | H3: 开票预警 | I3: 发票类型 | J3: 备注
A4: 1 | B4: 静象文旅 | C4: 110000 | D4: 66000 | E4: 0.6 | F4: 44000 | G4: 44000 | H4: 正常 | I4: 增值税专用发票
A5: 2 | B5: 滨海农商 | C5: 80000 | D5: 40000 | E5: 0.5 | F5: 40000 | G5: 40000 | H5: 正常 | I5: 增值税专用发票
A6: 3 | B6: 随行科技 | C6: 94400 | D6: 94400 | E6: 1 | F6: 0 | G6: 0 | H6: ✓ 开票完成 | I6: 增值税专用发票
A7: 4 | B7: 骏铭科技 | C7: 171000 | D7: 90000 | E7: 0.52631579 | F7: 81000 | G7: 81000 | H7: 正常 | I7: 增值税专用发票
A8: 5 | B8: 光电高斯 | C8: 225000 | D8: 108000 | E8: 0.48 | F8: 117000 | G8: 117000 | H8: 正常 | I8: 增值税专用发票
A9: 6 | B9: 中交疏浚 | C9: 180000 | D9: 72000 | E9: 0.4 | F9: 108000 | G9: 108000 | H9: 正常 | I9: 增值税专用发票
B10: 合计 | C10: =SUM(C4:C9) | D10: =SUM(D4:D9) | E10: =D10/C10 | F10: =SUM(F4:F9) | G10: =SUM(G4:G9)

Sheet 4.成本支出管理表
A1: 成本支出管理表
A3: 序号 | B3: 项目名称 | C3: 合同金额 | D3: 预算成本 | E3: 成本率 | F3: 已付款 | G3: 未付款 | H3: 付款进度 | I3: 成本预警 | J3: 成本控制状态 | K3: 备注
A4: 1 | B4: 静象文旅 | C4: 110000 | D4: 38000 | E4: 0.34545455 | F4: 11000 | G4: 27000 | H4: 0.28947368 | I4: ✓ 成本可控 | J4: 良好
A5: 2 | B5: 滨海农商 | C5: 80000 | D5: 45000 | E5: 0.5625 | F5: 0 | G5: 45000 | H5: 0 | I5: ✓ 成本可控 | J5: 良好
A6: 3 | B6: 随行科技 | C6: 94400 | D6: 40900 | E6: 0.43326271 | F6: 30900 | G6: 10000 | H6: 0.75550122 | I6: ✓ 成本可控 | J6: 良好
A7: 4 | B7: 骏铭科技 | C7: 171000 | D7: 40000 | E7: 0.23391813 | F7: 0 | G7: 40000 | H7: 0 | I7: ✓ 成本可控 | J7: 良好
A8: 5 | B8: 光电高斯 | C8: 225000 | D8: 58000 | E8: 0.25777778 | F8: 0 | G8: 58000 | H8: 0 | I8: ✓ 成本可控 | J8: 良好
A9: 6 | B9: 中交疏浚 | C9: 180000 | D9: 60000 | E9: 0.33333333 | F9: 0 | G9: 60000 | H9: 0 | I9: ✓ 成本可控 | J9: 良好
B10: 合计 | C10: =SUM(C4:C9) | D10: =SUM(D4:D9) | E10: =D10/C10 | F10: =SUM(F4:F9) | G10: =SUM(G4:G9) | H10: =F10/D10

Sheet 5.利润分析表
A1: 利润分析表
A3: 序号 | B3: 项目名称 | C3: 合同金额 | D3: 已收款金额 | E3: 预算成本 | F3: 已付款 | G3: 毛利润 | H3: 毛利率 | I3: 已确认利润 | J3: 利润实现率 | K3: 利润预警 | L3: 备注
A4: 1 | B4: 静象文旅 | C4: 110000 | D4: 66000 | E4: 38000 | F4: 11000 | G4: 72000 | H4: 0.65454545 | I4: 43200 | J4: 0.6 | K4: ✓ 利润良好
A5: 2 | B5: 滨海农商 | C5: 80000 | D5: 40000 | E5: 45000 | F5: 0 | G5: 35000 | H5: 0.4375 | I5: 17500 | J5: 0.5 | K5: ✓ 利润良好
A6: 3 | B6: 随行科技 | C6: 94400 | D6: 94400 | E6: 40900 | F6: 30900 | G6: 53500 | H6: 0.56673729 | I6: 53500 | J6: 1 | K6: ✓ 利润良好
A7: 4 | B7: 骏铭科技 | C7: 171000 | D7: 90000 | E7: 40000 | F7: 0 | G7: 131000 | H7: 0.76608187 | I7: 68947.368 | J7: 0.52631579 | K7: ✓ 利润良好
A8: 5 | B8: 光电高斯 | C8: 225000 | D8: 108000 | E8: 58000 | F8: 0 | G8: 167000 | H8: 0.74222222 | I8: 80160 | J8: 0.48 | K8: ✓ 利润良好
A9: 6 | B9: 中交疏浚 | C9: 180000 | D9: 0 | E9: 60000 | F9: 0 | G9: 120000 | H9: 0.66666667 | I9: 0 | J9: 0 | K9: ✓ 利润良好
B10: 合计 | C10: =SUM(C4:C9) | D10: =SUM(D4:D9) | E10: =SUM(E4:E9) | F10: =SUM(F4:F9) | G10: =C10-E10 | H10: =G10/C10 | I10: =SUM(I4:I9) | J10: =I10/G10

Sheet 6.预警分析表
A1: 预警分析表
A3: 序号 | B3: 项目名称 | C3: 合同金额 | D3: 收款进度 | E3: 开票进度 | F3: 成本率 | G3: 毛利率 | H3: 综合风险等级 | I3: 收款预警 | J3: 开票预警 | K3: 成本预警 | L3: 利润预警 | M3: 预警说明
A4: 1 | B4: 静象文旅 | C4: 110000 | D4: 0.6 | E4: 0.6 | F4: 0.34545455 | G4: 0.65454545 | H4: 低风险 | I4: ✓ 正常 | J4: ✓ 正常 | K4: ✓ 正常 | L4: ✓ 正常 | M4: 项目运行正常
A5: 2 | B5: 滨海农商 | C5: 80000 | D5: 0.5 | E5: 0.5 | F5: 0.5625 | G5: 0.4375 | H5: 低风险 | I5: ✓ 正常 | J5: ✓ 正常 | K5: ✓ 正常 | L5: ✓ 正常 | M5: 项目运行正常
A6: 3 | B6: 随行科技 | C6: 94400 | D6: 1 | E6: 1 | F6: 0.43326271 | G6: 0.56673729 | H6: 低风险 | I6: ✓ 正常 | J6: ✓ 正常 | K6: ✓ 正常 | L6: ✓ 正常 | M6: 项目运行正常
A7: 4 | B7: 骏铭科技 | C7: 171000 | D7: 0.52631579 | E7: 0.52631579 | F7: 0.23391813 | G7: 0.76608187 | H7: 低风险 | I7: ✓ 正常 | J7: ✓ 正常 | K7: ✓ 正常 | L7: ✓ 正常 | M7: 项目运行正常
A8: 5 | B8: 光电高斯 | C8: 225000 | D8: 0.48 | E8: 0.48 | F8: 0.25777778 | G8: 0.74222222 | H8: 中风险 | I8: △ 进度慢 | J8: ✓ 正常 | K8: ✓ 正常 | L8: ✓ 正常 | M8: 需关注: 收款
A9: 6 | B9: 中交疏浚 | C9: 180000 | D9: 0 | E9: 0.4 | F9: 0.33333333 | G9: 0.66666667 | H9: 中风险 | I9: ⚠ 未收款 | J9: ✓ 正常 | K9: ✓ 正常 | L9: ✓ 正常 | M9: 需关注: 收款
B11: 预警统计
B12: 高风险项目数 | C12: =COUNTIF(H4:H9,"高风险")
B13: 中风险项目数 | C13: =COUNTIF(H4:H9,"中风险")
B14: 低风险项目数 | C14: =COUNTIF(H4:H9,"低风险")

Sheet 8.成本明细表
A1: 成本明细表
A3: 序号 | B3: 所属项目 | C3: 成本项名称 | D3: 成本金额 | E3: 已付款 | F3: 未付款 | G3: 付款进度 | H3: 供应商
A4: 1 | B4: 静象文旅 | C4: 静象——合规认定专项服务合同——北京中闻 | D4: 2000 | E4: 0 | F4: 2000 | G4: 0 | H4: 北京中闻
A5: 2 | B5: 静象文旅 | C5: 静象——价值评估专项服务合同——方圆 | D5: 10000 | E5: 0 | F5: 10000 | G5: 0 | H5: 方圆
A6: 3 | B6: 静象文旅 | C6: 静象——审计核验专项服务合同——中合诚 | D6: 10000 | E6: 0 | F6: 10000 | G6: 0 | H6: 中合诚
A7: 4 | B7: 静象文旅 | C7: 静象——数据评价专项服务合同——通广云合 | D7: 5000 | E7: 0 | F7: 5000 | G7: 0 | H7: 通广云合
A8: 5 | B8: 静象文旅 | C8: 静象——数据资产评估专项合作协议——天津数据资产登记评估中心 | D8: 11000 | E8: 11000 | F8: 0 | G8: 1 | H8: 天津数据资产登记评估中心
A9: 6 | B9: 滨海农商 | C9: 滨农——合规认定法律服务合同——北京大成 | D9: 5000 | E9: 0 | F9: 5000 | G9: 0 | H9: 北京大成
A10: 7 | B10: 滨海农商 | C10: 滨农——价值评估专项服务合同——天津方圆 | D10: 10000 | E10: 0 | F10: 10000 | G10: 0 | H10: 天津方圆
A11: 8 | B11: 滨海农商 | C11: 滨农——数据评价报告服务合同——国家信息中心 | D11: 10000 | E11: 0 | F11: 10000 | G11: 0 | H11: 国家信息中心
A12: 9 | B12: 滨海农商 | C12: 滨农——数据资产审计核验服务合同——中审华 | D12: 10000 | E12: 0 | F12: 10000 | G12: 0 | H12: 中审华
A13: 10 | B13: 滨海农商 | C13: 滨农——数据资产审计核验服务合同——中审华 | D13: 10000 | E13: 0 | F13: 10000 | G13: 0 | H13: 中审华
A14: 11 | B14: 随行科技 | C14: 随行——价值评估专项服务合同——中兴财 | D14: 8000 | E14: 8000 | F14: 0 | G14: 1 | H14: 中兴财
A15: 12 | B15: 随行科技 | C15: 随行——审计核验专项服务合同——祥和 | D15: 7000 | E15: 7000 | F15: 0 | G15: 1 | H15: 祥和
... A33: 30 | B33: 天保热电 | C33: 天保热电——资产评估专项服务合同——博成评估【未签合同，暂估】 | D33: 10000 | E33: 0 | F33: 10000 | G33: 0 | H33: 博成评估【未签合同，暂估】
B34: 合计 | D34: =SUM(D4:D33) | E34: =SUM(E4:E33) | F34: =SUM(F4:F33) | G34: =E34/D34
